target_json.py
target_json-0.0.2.dist-info/DESCRIPTION.rst
target_json-0.0.2.dist-info/METADATA
target_json-0.0.2.dist-info/RECORD
target_json-0.0.2.dist-info/WHEEL
target_json-0.0.2.dist-info/entry_points.txt
target_json-0.0.2.dist-info/metadata.json
target_json-0.0.2.dist-info/top_level.txt
