Metadata-Version: 2.0
Name: target-json
Version: 0.0.2
Summary: Singer.io target for writing JSON files
Home-page: https://singer.io
Author: dvelardez
Author-email: UNKNOWN
License: UNKNOWN
Platform: UNKNOWN
Classifier: Programming Language :: Python :: 3 :: Only
Requires-Dist: jsonschema (==2.6.0)
Requires-Dist: singer-python (==5.0.4)
